{"nodes": [{"id": "base", "label": "base.py", "file_type": "code", "source_file": "src/application/depreciation/calculators/base.py", "source_location": "L1"}, {"id": "base_statetransitionerror", "label": "StateTransitionError", "file_type": "code", "source_file": "src/application/depreciation/calculators/base.py", "source_location": "L23"}, {"id": "exception", "label": "Exception", "file_type": "code", "source_file": "", "source_location": ""}, {"id": "base_statetransitionerror_init", "label": ".__init__()", "file_type": "code", "source_file": "src/application/depreciation/calculators/base.py", "source_location": "L26"}, {"id": "base_transitioninput", "label": "TransitionInput", "file_type": "code", "source_file": "src/application/depreciation/calculators/base.py", "source_location": "L34"}, {"id": "base_basedepreciationcalculator", "label": "BaseDepreciationCalculator", "file_type": "code", "source_file": "src/application/depreciation/calculators/base.py", "source_location": "L42"}, {"id": "abc", "label": "ABC", "file_type": "code", "source_file": "", "source_location": ""}, {"id": "base_basedepreciationcalculator_init", "label": ".__init__()", "file_type": "code", "source_file": "src/application/depreciation/calculators/base.py", "source_location": "L50"}, {"id": "base_calculate_depreciation", "label": "calculate_depreciation()", "file_type": "code", "source_file": "src/application/depreciation/calculators/base.py", "source_location": "L55"}, {"id": "base_get_transition_rules", "label": "_get_transition_rules()", "file_type": "code", "source_file": "src/application/depreciation/calculators/base.py", "source_location": "L65"}, {"id": "base_basedepreciationcalculator_load_transition_rules", "label": "._load_transition_rules()", "file_type": "code", "source_file": "src/application/depreciation/calculators/base.py", "source_location": "L80"}, {"id": "base_basedepreciationcalculator_transition", "label": ".transition()", "file_type": "code", "source_file": "src/application/depreciation/calculators/base.py", "source_location": "L89"}, {"id": "base_basedepreciationcalculator_evaluate_guard", "label": "._evaluate_guard()", "file_type": "code", "source_file": "src/application/depreciation/calculators/base.py", "source_location": "L134"}, {"id": "base_basedepreciationcalculator_list_allowed_transitions", "label": ".list_allowed_transitions()", "file_type": "code", "source_file": "src/application/depreciation/calculators/base.py", "source_location": "L149"}, {"id": "base_rationale_1", "label": "Base depreciation calculator and state transition engine for asset lifecycle man", "file_type": "rationale", "source_file": "src/application/depreciation/calculators/base.py", "source_location": "L1"}, {"id": "base_rationale_24", "label": "Raised when a state transition is invalid or not permitted.", "file_type": "rationale", "source_file": "src/application/depreciation/calculators/base.py", "source_location": "L24"}, {"id": "base_rationale_35", "label": "Input bundle for a state transition.", "file_type": "rationale", "source_file": "src/application/depreciation/calculators/base.py", "source_location": "L35"}, {"id": "base_rationale_43", "label": "Abstract base calculator for depreciation methods.      Concrete calculators mus", "file_type": "rationale", "source_file": "src/application/depreciation/calculators/base.py", "source_location": "L43"}, {"id": "base_rationale_56", "label": "Compute depreciation values for the given asset up to period_end.          Retur", "file_type": "rationale", "source_file": "src/application/depreciation/calculators/base.py", "source_location": "L56"}, {"id": "base_rationale_66", "label": "Define allowed state transitions for this calculator.          Example:", "file_type": "rationale", "source_file": "src/application/depreciation/calculators/base.py", "source_location": "L66"}, {"id": "base_rationale_81", "label": "Load and cache transition rules; fallback to empty map if unavailable.", "file_type": "rationale", "source_file": "src/application/depreciation/calculators/base.py", "source_location": "L81"}, {"id": "base_rationale_96", "label": "Validate and execute a deterministic state transition.          Guarantees:", "file_type": "rationale", "source_file": "src/application/depreciation/calculators/base.py", "source_location": "L96"}, {"id": "base_rationale_135", "label": "Evaluate a guard by name against runtime context.          Default implementatio", "file_type": "rationale", "source_file": "src/application/depreciation/calculators/base.py", "source_location": "L135"}, {"id": "base_rationale_150", "label": "Return all target statuses reachable from the given status.", "file_type": "rationale", "source_file": "src/application/depreciation/calculators/base.py", "source_location": "L150"}], "edges": [{"source": "base", "target": "abc", "relation": "imports_from", "confidence": "EXTRACTED", "source_file": "src/application/depreciation/calculators/base.py", "source_location": "L11", "weight": 1.0}, {"source": "base", "target": "dataclasses", "relation": "imports_from", "confidence": "EXTRACTED", "source_file": "src/application/depreciation/calculators/base.py", "source_location": "L12", "weight": 1.0}, {"source": "base", "target": "datetime", "relation": "imports_from", "confidence": "EXTRACTED", "source_file": "src/application/depreciation/calculators/base.py", "source_location": "L13", "weight": 1.0}, {"source": "base", "target": "typing", "relation": "imports_from", "confidence": "EXTRACTED", "source_file": "src/application/depreciation/calculators/base.py", "source_location": "L14", "weight": 1.0}, {"source": "base", "target": "src_domain_entities_asset", "relation": "imports_from", "confidence": "EXTRACTED", "source_file": "src/application/depreciation/calculators/base.py", "source_location": "L16", "weight": 1.0}, {"source": "base", "target": "src_domain_entities_retirement_request", "relation": "imports_from", "confidence": "EXTRACTED", "source_file": "src/application/depreciation/calculators/base.py", "source_location": "L17", "weight": 1.0}, {"source": "base", "target": "src_domain_services_status_history_service", "relation": "imports_from", "confidence": "EXTRACTED", "source_file": "src/application/depreciation/calculators/base.py", "source_location": "L18", "weight": 1.0}, {"source": "base", "target": "src_domain_value_objects_asset_status", "relation": "imports_from", "confidence": "EXTRACTED", "source_file": "src/application/depreciation/calculators/base.py", "source_location": "L19", "weight": 1.0}, {"source": "base", "target": "src_domain_value_objects_transition_rule", "relation": "imports_from", "confidence": "EXTRACTED", "source_file": "src/application/depreciation/calculators/base.py", "source_location": "L20", "weight": 1.0}, {"source": "base", "target": "base_statetransitionerror", "relation": "contains", "confidence": "EXTRACTED", "source_file": "src/application/depreciation/calculators/base.py", "source_location": "L23", "weight": 1.0}, {"source": "base_statetransitionerror", "target": "exception", "relation": "inherits", "confidence": "EXTRACTED", "source_file": "src/application/depreciation/calculators/base.py", "source_location": "L23", "weight": 1.0}, {"source": "base_statetransitionerror", "target": "base_statetransitionerror_init", "relation": "method", "confidence": "EXTRACTED", "source_file": "src/application/depreciation/calculators/base.py", "source_location": "L26", "weight": 1.0}, {"source": "base", "target": "base_transitioninput", "relation": "contains", "confidence": "EXTRACTED", "source_file": "src/application/depreciation/calculators/base.py", "source_location": "L34", "weight": 1.0}, {"source": "base", "target": "base_basedepreciationcalculator", "relation": "contains", "confidence": "EXTRACTED", "source_file": "src/application/depreciation/calculators/base.py", "source_location": "L42", "weight": 1.0}, {"source": "base_basedepreciationcalculator", "target": "abc", "relation": "inherits", "confidence": "EXTRACTED", "source_file": "src/application/depreciation/calculators/base.py", "source_location": "L42", "weight": 1.0}, {"source": "base_basedepreciationcalculator", "target": "base_basedepreciationcalculator_init", "relation": "method", "confidence": "EXTRACTED", "source_file": "src/application/depreciation/calculators/base.py", "source_location": "L50", "weight": 1.0}, {"source": "base", "target": "base_calculate_depreciation", "relation": "contains", "confidence": "EXTRACTED", "source_file": "src/application/depreciation/calculators/base.py", "source_location": "L55", "weight": 1.0}, {"source": "base", "target": "base_get_transition_rules", "relation": "contains", "confidence": "EXTRACTED", "source_file": "src/application/depreciation/calculators/base.py", "source_location": "L65", "weight": 1.0}, {"source": "base_basedepreciationcalculator", "target": "base_basedepreciationcalculator_load_transition_rules", "relation": "method", "confidence": "EXTRACTED", "source_file": "src/application/depreciation/calculators/base.py", "source_location": "L80", "weight": 1.0}, {"source": "base_basedepreciationcalculator", "target": "base_basedepreciationcalculator_transition", "relation": "method", "confidence": "EXTRACTED", "source_file": "src/application/depreciation/calculators/base.py", "source_location": "L89", "weight": 1.0}, {"source": "base_basedepreciationcalculator", "target": "base_basedepreciationcalculator_evaluate_guard", "relation": "method", "confidence": "EXTRACTED", "source_file": "src/application/depreciation/calculators/base.py", "source_location": "L134", "weight": 1.0}, {"source": "base_basedepreciationcalculator", "target": "base_basedepreciationcalculator_list_allowed_transitions", "relation": "method", "confidence": "EXTRACTED", "source_file": "src/application/depreciation/calculators/base.py", "source_location": "L149", "weight": 1.0}, {"source": "base_statetransitionerror_init", "target": "base_basedepreciationcalculator_init", "relation": "calls", "confidence": "EXTRACTED", "source_file": "src/application/depreciation/calculators/base.py", "source_location": "L30", "weight": 1.0}, {"source": "base_basedepreciationcalculator_init", "target": "base_basedepreciationcalculator_load_transition_rules", "relation": "calls", "confidence": "EXTRACTED", "source_file": "src/application/depreciation/calculators/base.py", "source_location": "L52", "weight": 1.0}, {"source": "base_basedepreciationcalculator_load_transition_rules", "target": "base_get_transition_rules", "relation": "calls", "confidence": "EXTRACTED", "source_file": "src/application/depreciation/calculators/base.py", "source_location": "L83", "weight": 1.0}, {"source": "base_basedepreciationcalculator_transition", "target": "base_statetransitionerror", "relation": "calls", "confidence": "EXTRACTED", "source_file": "src/application/depreciation/calculators/base.py", "source_location": "L107", "weight": 1.0}, {"source": "base_basedepreciationcalculator_transition", "target": "base_basedepreciationcalculator_evaluate_guard", "relation": "calls", "confidence": "EXTRACTED", "source_file": "src/application/depreciation/calculators/base.py", "source_location": "L116", "weight": 1.0}, {"source": "base_rationale_1", "target": "base", "relation": "rationale_for", "confidence": "EXTRACTED", "source_file": "src/application/depreciation/calculators/base.py", "source_location": "L1", "weight": 1.0}, {"source": "base_rationale_24", "target": "base_statetransitionerror", "relation": "rationale_for", "confidence": "EXTRACTED", "source_file": "src/application/depreciation/calculators/base.py", "source_location": "L24", "weight": 1.0}, {"source": "base_rationale_35", "target": "base_transitioninput", "relation": "rationale_for", "confidence": "EXTRACTED", "source_file": "src/application/depreciation/calculators/base.py", "source_location": "L35", "weight": 1.0}, {"source": "base_rationale_43", "target": "base_basedepreciationcalculator", "relation": "rationale_for", "confidence": "EXTRACTED", "source_file": "src/application/depreciation/calculators/base.py", "source_location": "L43", "weight": 1.0}, {"source": "base_rationale_56", "target": "base_basedepreciationcalculator_calculate_depreciation", "relation": "rationale_for", "confidence": "EXTRACTED", "source_file": "src/application/depreciation/calculators/base.py", "source_location": "L56", "weight": 1.0}, {"source": "base_rationale_66", "target": "base_basedepreciationcalculator_get_transition_rules", "relation": "rationale_for", "confidence": "EXTRACTED", "source_file": "src/application/depreciation/calculators/base.py", "source_location": "L66", "weight": 1.0}, {"source": "base_rationale_81", "target": "base_basedepreciationcalculator_load_transition_rules", "relation": "rationale_for", "confidence": "EXTRACTED", "source_file": "src/application/depreciation/calculators/base.py", "source_location": "L81", "weight": 1.0}, {"source": "base_rationale_96", "target": "base_basedepreciationcalculator_transition", "relation": "rationale_for", "confidence": "EXTRACTED", "source_file": "src/application/depreciation/calculators/base.py", "source_location": "L96", "weight": 1.0}, {"source": "base_rationale_135", "target": "base_basedepreciationcalculator_evaluate_guard", "relation": "rationale_for", "confidence": "EXTRACTED", "source_file": "src/application/depreciation/calculators/base.py", "source_location": "L135", "weight": 1.0}, {"source": "base_rationale_150", "target": "base_basedepreciationcalculator_list_allowed_transitions", "relation": "rationale_for", "confidence": "EXTRACTED", "source_file": "src/application/depreciation/calculators/base.py", "source_location": "L150", "weight": 1.0}]}