{"nodes": [{"id": "notification_service", "label": "notification_service.py", "file_type": "code", "source_file": "src/services/notification_service.py", "source_location": "L1"}, {"id": "notification_service_notificationservice", "label": "NotificationService", "file_type": "code", "source_file": "src/services/notification_service.py", "source_location": "L16"}, {"id": "notification_service_notificationservice_init", "label": ".__init__()", "file_type": "code", "source_file": "src/services/notification_service.py", "source_location": "L19"}, {"id": "notification_service_notificationservice_notify_status_change", "label": ".notify_status_change()", "file_type": "code", "source_file": "src/services/notification_service.py", "source_location": "L28"}, {"id": "notification_service_notificationservice_notify_approval_required", "label": ".notify_approval_required()", "file_type": "code", "source_file": "src/services/notification_service.py", "source_location": "L55"}, {"id": "notification_service_notificationservice_notify_approval_outcome", "label": ".notify_approval_outcome()", "file_type": "code", "source_file": "src/services/notification_service.py", "source_location": "L80"}, {"id": "notification_service_notificationservice_notify_retirement_complete", "label": ".notify_retirement_complete()", "file_type": "code", "source_file": "src/services/notification_service.py", "source_location": "L107"}, {"id": "notification_service_notificationservice_send_internal_notification", "label": "._send_internal_notification()", "file_type": "code", "source_file": "src/services/notification_service.py", "source_location": "L127"}, {"id": "notification_service_rationale_1", "label": "Notification Service for Asset Retirement Workflow.  This module handles notific", "file_type": "rationale", "source_file": "src/services/notification_service.py", "source_location": "L1"}, {"id": "notification_service_rationale_17", "label": "Service responsible for sending notifications during asset retirement flow.", "file_type": "rationale", "source_file": "src/services/notification_service.py", "source_location": "L17"}, {"id": "notification_service_rationale_20", "label": "Initialize NotificationService.          Args:             retirement_service: B", "file_type": "rationale", "source_file": "src/services/notification_service.py", "source_location": "L20"}, {"id": "notification_service_rationale_35", "label": "Notify stakeholders about an asset status change.          This is invoked by th", "file_type": "rationale", "source_file": "src/services/notification_service.py", "source_location": "L35"}, {"id": "notification_service_rationale_61", "label": "Notify an approver that an action is required.          Sent when an asset enter", "file_type": "rationale", "source_file": "src/services/notification_service.py", "source_location": "L61"}, {"id": "notification_service_rationale_88", "label": "Notify stakeholders about an approval decision.          Args:             appro", "file_type": "rationale", "source_file": "src/services/notification_service.py", "source_location": "L88"}, {"id": "notification_service_rationale_112", "label": "Notify that an asset has been fully retired and written off.          Args:", "file_type": "rationale", "source_file": "src/services/notification_service.py", "source_location": "L112"}, {"id": "notification_service_rationale_128", "label": "Placeholder for internal notification delivery.          In production, this wou", "file_type": "rationale", "source_file": "src/services/notification_service.py", "source_location": "L128"}, {"id": "notification_service_rationale_52", "label": "# TODO: Integrate with actual notification channels (email, Slack, etc.)", "file_type": "rationale", "source_file": "src/services/notification_service.py", "source_location": "L52"}, {"id": "notification_service_rationale_77", "label": "# TODO: Integrate with actual notification channels (email, Slack, etc.)", "file_type": "rationale", "source_file": "src/services/notification_service.py", "source_location": "L77"}, {"id": "notification_service_rationale_104", "label": "# TODO: Integrate with actual notification channels (email, Slack, etc.)", "file_type": "rationale", "source_file": "src/services/notification_service.py", "source_location": "L104"}, {"id": "notification_service_rationale_124", "label": "# TODO: Integrate with actual notification channels (email, Slack, etc.)", "file_type": "rationale", "source_file": "src/services/notification_service.py", "source_location": "L124"}, {"id": "notification_service_rationale_134", "label": "# TODO: Implement actual delivery mechanism", "file_type": "rationale", "source_file": "src/services/notification_service.py", "source_location": "L134"}], "edges": [{"source": "notification_service", "target": "logging", "relation": "imports", "confidence": "EXTRACTED", "source_file": "src/services/notification_service.py", "source_location": "L8", "weight": 1.0}, {"source": "notification_service", "target": "typing", "relation": "imports_from", "confidence": "EXTRACTED", "source_file": "src/services/notification_service.py", "source_location": "L9", "weight": 1.0}, {"source": "notification_service", "target": "src_domain_entities_asset", "relation": "imports_from", "confidence": "EXTRACTED", "source_file": "src/services/notification_service.py", "source_location": "L11", "weight": 1.0}, {"source": "notification_service", "target": "src_domain_entities_retirement", "relation": "imports_from", "confidence": "EXTRACTED", "source_file": "src/services/notification_service.py", "source_location": "L12", "weight": 1.0}, {"source": "notification_service", "target": "src_domain_services_retirement_service", "relation": "imports_from", "confidence": "EXTRACTED", "source_file": "src/services/notification_service.py", "source_location": "L13", "weight": 1.0}, {"source": "notification_service", "target": "notification_service_notificationservice", "relation": "contains", "confidence": "EXTRACTED", "source_file": "src/services/notification_service.py", "source_location": "L16", "weight": 1.0}, {"source": "notification_service_notificationservice", "target": "notification_service_notificationservice_init", "relation": "method", "confidence": "EXTRACTED", "source_file": "src/services/notification_service.py", "source_location": "L19", "weight": 1.0}, {"source": "notification_service_notificationservice", "target": "notification_service_notificationservice_notify_status_change", "relation": "method", "confidence": "EXTRACTED", "source_file": "src/services/notification_service.py", "source_location": "L28", "weight": 1.0}, {"source": "notification_service_notificationservice", "target": "notification_service_notificationservice_notify_approval_required", "relation": "method", "confidence": "EXTRACTED", "source_file": "src/services/notification_service.py", "source_location": "L55", "weight": 1.0}, {"source": "notification_service_notificationservice", "target": "notification_service_notificationservice_notify_approval_outcome", "relation": "method", "confidence": "EXTRACTED", "source_file": "src/services/notification_service.py", "source_location": "L80", "weight": 1.0}, {"source": "notification_service_notificationservice", "target": "notification_service_notificationservice_notify_retirement_complete", "relation": "method", "confidence": "EXTRACTED", "source_file": "src/services/notification_service.py", "source_location": "L107", "weight": 1.0}, {"source": "notification_service_notificationservice", "target": "notification_service_notificationservice_send_internal_notification", "relation": "method", "confidence": "EXTRACTED", "source_file": "src/services/notification_service.py", "source_location": "L127", "weight": 1.0}, {"source": "notification_service_notificationservice_notify_status_change", "target": "notification_service_notificationservice_send_internal_notification", "relation": "calls", "confidence": "EXTRACTED", "source_file": "src/services/notification_service.py", "source_location": "L53", "weight": 1.0}, {"source": "notification_service_notificationservice_notify_approval_required", "target": "notification_service_notificationservice_send_internal_notification", "relation": "calls", "confidence": "EXTRACTED", "source_file": "src/services/notification_service.py", "source_location": "L78", "weight": 1.0}, {"source": "notification_service_notificationservice_notify_approval_outcome", "target": "notification_service_notificationservice_send_internal_notification", "relation": "calls", "confidence": "EXTRACTED", "source_file": "src/services/notification_service.py", "source_location": "L105", "weight": 1.0}, {"source": "notification_service_notificationservice_notify_retirement_complete", "target": "notification_service_notificationservice_send_internal_notification", "relation": "calls", "confidence": "EXTRACTED", "source_file": "src/services/notification_service.py", "source_location": "L125", "weight": 1.0}, {"source": "notification_service_rationale_1", "target": "notification_service", "relation": "rationale_for", "confidence": "EXTRACTED", "source_file": "src/services/notification_service.py", "source_location": "L1", "weight": 1.0}, {"source": "notification_service_rationale_17", "target": "notification_service_notificationservice", "relation": "rationale_for", "confidence": "EXTRACTED", "source_file": "src/services/notification_service.py", "source_location": "L17", "weight": 1.0}, {"source": "notification_service_rationale_20", "target": "notification_service_notificationservice_init", "relation": "rationale_for", "confidence": "EXTRACTED", "source_file": "src/services/notification_service.py", "source_location": "L20", "weight": 1.0}, {"source": "notification_service_rationale_35", "target": "notification_service_notificationservice_notify_status_change", "relation": "rationale_for", "confidence": "EXTRACTED", "source_file": "src/services/notification_service.py", "source_location": "L35", "weight": 1.0}, {"source": "notification_service_rationale_61", "target": "notification_service_notificationservice_notify_approval_required", "relation": "rationale_for", "confidence": "EXTRACTED", "source_file": "src/services/notification_service.py", "source_location": "L61", "weight": 1.0}, {"source": "notification_service_rationale_88", "target": "notification_service_notificationservice_notify_approval_outcome", "relation": "rationale_for", "confidence": "EXTRACTED", "source_file": "src/services/notification_service.py", "source_location": "L88", "weight": 1.0}, {"source": "notification_service_rationale_112", "target": "notification_service_notificationservice_notify_retirement_complete", "relation": "rationale_for", "confidence": "EXTRACTED", "source_file": "src/services/notification_service.py", "source_location": "L112", "weight": 1.0}, {"source": "notification_service_rationale_128", "target": "notification_service_notificationservice_send_internal_notification", "relation": "rationale_for", "confidence": "EXTRACTED", "source_file": "src/services/notification_service.py", "source_location": "L128", "weight": 1.0}, {"source": "notification_service_rationale_52", "target": "notification_service", "relation": "rationale_for", "confidence": "EXTRACTED", "source_file": "src/services/notification_service.py", "source_location": "L52", "weight": 1.0}, {"source": "notification_service_rationale_77", "target": "notification_service", "relation": "rationale_for", "confidence": "EXTRACTED", "source_file": "src/services/notification_service.py", "source_location": "L77", "weight": 1.0}, {"source": "notification_service_rationale_104", "target": "notification_service", "relation": "rationale_for", "confidence": "EXTRACTED", "source_file": "src/services/notification_service.py", "source_location": "L104", "weight": 1.0}, {"source": "notification_service_rationale_124", "target": "notification_service", "relation": "rationale_for", "confidence": "EXTRACTED", "source_file": "src/services/notification_service.py", "source_location": "L124", "weight": 1.0}, {"source": "notification_service_rationale_134", "target": "notification_service", "relation": "rationale_for", "confidence": "EXTRACTED", "source_file": "src/services/notification_service.py", "source_location": "L134", "weight": 1.0}]}