{"nodes": [{"id": "retirement", "label": "retirement.py", "file_type": "code", "source_file": "src/models/retirement.py", "source_location": "L1"}, {"id": "retirement_retirementrequest", "label": "RetirementRequest", "file_type": "code", "source_file": "src/models/retirement.py", "source_location": "L16"}, {"id": "retirement_retirementhistory", "label": "RetirementHistory", "file_type": "code", "source_file": "src/models/retirement.py", "source_location": "L27"}, {"id": "retirement_assetretirement", "label": "AssetRetirement", "file_type": "code", "source_file": "src/models/retirement.py", "source_location": "L38"}, {"id": "retirement_create_retirement_request", "label": "create_retirement_request()", "file_type": "code", "source_file": "src/models/retirement.py", "source_location": "L47"}, {"id": "retirement_transition_retirement_status", "label": "transition_retirement_status()", "file_type": "code", "source_file": "src/models/retirement.py", "source_location": "L76"}, {"id": "retirement_build_retirement_summary", "label": "build_retirement_summary()", "file_type": "code", "source_file": "src/models/retirement.py", "source_location": "L101"}, {"id": "retirement_rationale_1", "label": "Retirement Domain Models  This module defines data models related to asset retir", "file_type": "rationale", "source_file": "src/models/retirement.py", "source_location": "L1"}, {"id": "retirement_rationale_17", "label": "Retirement request submitted by a user.", "file_type": "rationale", "source_file": "src/models/retirement.py", "source_location": "L17"}, {"id": "retirement_rationale_28", "label": "Historical record of a retirement state transition.", "file_type": "rationale", "source_file": "src/models/retirement.py", "source_location": "L28"}, {"id": "retirement_rationale_39", "label": "Materialized view of a completed retirement.", "file_type": "rationale", "source_file": "src/models/retirement.py", "source_location": "L39"}, {"id": "retirement_rationale_53", "label": "Create a new retirement request.      Args:         asset_id: The unique identif", "file_type": "rationale", "source_file": "src/models/retirement.py", "source_location": "L53"}, {"id": "retirement_rationale_81", "label": "Record a status transition for a retirement request.      Args:         retireme", "file_type": "rationale", "source_file": "src/models/retirement.py", "source_location": "L81"}, {"id": "retirement_rationale_104", "label": "Build a lightweight summary for dashboard consumption.      Args:         retire", "file_type": "rationale", "source_file": "src/models/retirement.py", "source_location": "L104"}], "edges": [{"source": "retirement", "target": "dataclasses", "relation": "imports_from", "confidence": "EXTRACTED", "source_file": "src/models/retirement.py", "source_location": "L9", "weight": 1.0}, {"source": "retirement", "target": "datetime", "relation": "imports_from", "confidence": "EXTRACTED", "source_file": "src/models/retirement.py", "source_location": "L10", "weight": 1.0}, {"source": "retirement", "target": "typing", "relation": "imports_from", "confidence": "EXTRACTED", "source_file": "src/models/retirement.py", "source_location": "L11", "weight": 1.0}, {"source": "retirement", "target": "uuid", "relation": "imports_from", "confidence": "EXTRACTED", "source_file": "src/models/retirement.py", "source_location": "L12", "weight": 1.0}, {"source": "retirement", "target": "retirement_retirementrequest", "relation": "contains", "confidence": "EXTRACTED", "source_file": "src/models/retirement.py", "source_location": "L16", "weight": 1.0}, {"source": "retirement", "target": "retirement_retirementhistory", "relation": "contains", "confidence": "EXTRACTED", "source_file": "src/models/retirement.py", "source_location": "L27", "weight": 1.0}, {"source": "retirement", "target": "retirement_assetretirement", "relation": "contains", "confidence": "EXTRACTED", "source_file": "src/models/retirement.py", "source_location": "L38", "weight": 1.0}, {"source": "retirement", "target": "retirement_create_retirement_request", "relation": "contains", "confidence": "EXTRACTED", "source_file": "src/models/retirement.py", "source_location": "L47", "weight": 1.0}, {"source": "retirement", "target": "retirement_transition_retirement_status", "relation": "contains", "confidence": "EXTRACTED", "source_file": "src/models/retirement.py", "source_location": "L76", "weight": 1.0}, {"source": "retirement", "target": "retirement_build_retirement_summary", "relation": "contains", "confidence": "EXTRACTED", "source_file": "src/models/retirement.py", "source_location": "L101", "weight": 1.0}, {"source": "retirement_create_retirement_request", "target": "retirement_retirementrequest", "relation": "calls", "confidence": "EXTRACTED", "source_file": "src/models/retirement.py", "source_location": "L66", "weight": 1.0}, {"source": "retirement_transition_retirement_status", "target": "retirement_retirementhistory", "relation": "calls", "confidence": "EXTRACTED", "source_file": "src/models/retirement.py", "source_location": "L91", "weight": 1.0}, {"source": "retirement_rationale_1", "target": "retirement", "relation": "rationale_for", "confidence": "EXTRACTED", "source_file": "src/models/retirement.py", "source_location": "L1", "weight": 1.0}, {"source": "retirement_rationale_17", "target": "retirement_retirementrequest", "relation": "rationale_for", "confidence": "EXTRACTED", "source_file": "src/models/retirement.py", "source_location": "L17", "weight": 1.0}, {"source": "retirement_rationale_28", "target": "retirement_retirementhistory", "relation": "rationale_for", "confidence": "EXTRACTED", "source_file": "src/models/retirement.py", "source_location": "L28", "weight": 1.0}, {"source": "retirement_rationale_39", "target": "retirement_assetretirement", "relation": "rationale_for", "confidence": "EXTRACTED", "source_file": "src/models/retirement.py", "source_location": "L39", "weight": 1.0}, {"source": "retirement_rationale_53", "target": "retirement_create_retirement_request", "relation": "rationale_for", "confidence": "EXTRACTED", "source_file": "src/models/retirement.py", "source_location": "L53", "weight": 1.0}, {"source": "retirement_rationale_81", "target": "retirement_transition_retirement_status", "relation": "rationale_for", "confidence": "EXTRACTED", "source_file": "src/models/retirement.py", "source_location": "L81", "weight": 1.0}, {"source": "retirement_rationale_104", "target": "retirement_build_retirement_summary", "relation": "rationale_for", "confidence": "EXTRACTED", "source_file": "src/models/retirement.py", "source_location": "L104", "weight": 1.0}]}